IRIXS/__init__.py
IRIXS/instrument_rowland.py
IRIXS/instrument_spectrograph.py
IRIXS/oneshot.py
IRIXS/p01plot.py
IRIXS/tools.py
IRIXS/ub.py
IRIXS-0.6.8.dist-info/LICENSE
IRIXS-0.6.8.dist-info/METADATA
IRIXS-0.6.8.dist-info/WHEEL
IRIXS-0.6.8.dist-info/entry_points.txt
IRIXS-0.6.8.dist-info/top_level.txt
IRIXS-0.6.8.dist-info/RECORD
