Metadata-Version: 2.1
Name: IRIXS
Version: 0.6.8
Summary: Routines for the IRIXS spectrometer
Home-page: http://github.com/djlns/irixs
Author: Joel Bertinshaw
Author-email: djlns@posteo.net
License: GNU GPLv3
Platform: UNKNOWN
Classifier: Development Status :: 4 - Beta
Classifier: Intended Audience :: Science/Research
Classifier: Natural Language :: English
Classifier: Operating System :: OS Independent
Classifier: Programming Language :: Python :: 3
Classifier: License :: OSI Approved :: GNU General Public License v3 or later (GPLv3+)
Classifier: Topic :: Scientific/Engineering :: Physics
Classifier: Topic :: Scientific/Engineering :: Image Processing
Classifier: Topic :: Scientific/Engineering :: Visualization
Requires-Dist: numpy (>=1.18)
Requires-Dist: matplotlib (>=3.1)
Requires-Dist: scipy (>=1.4)
Requires-Dist: scikit-image (>=0.16)
Requires-Dist: PyQt5 (>=5.9)
Requires-Dist: tabulate (>=0.8)
